uglierpty/__init__.py
uglierpty/__main__.py
uglierpty/dialogs/__init__.py
uglierpty/dialogs/add_session_dialog.py
uglierpty/dialogs/edit_session_dialog.py
uglierpty/session_manager/__init__.py
uglierpty/session_manager/session_manager.py
uglierpty/terminal/__init__.py
uglierpty/terminal/backend.py
uglierpty/terminal/widget.py
uglierpty/ui/__init__.py
uglierpty/ui/context_menus.py
uglierpty/ui/credentials_dialog.py
uglierpty/ui/creds_dlg.py
uglierpty/ui/creds_widget.py
uglierpty/ui/main_window.py
uglierpty/utils/__init__.py
uglierpty/utils/db.py
uglierpty/utils/db_utils.py
uglierpty/utils/models.py
uglierpty/utils/yaml_utils.py
uglierpty-0.3.dist-info/METADATA
uglierpty-0.3.dist-info/WHEEL
uglierpty-0.3.dist-info/top_level.txt
uglierpty-0.3.dist-info/RECORD
