Metadata-Version: 2.1
Name: uglierpty
Version: 0.3
Summary: UglierPTY - A Really Ugly PyQt6-based SSH Terminal
Home-page: https://github.com/scottpeterman/UglierPTY
Author: Scott Peterman
Author-email: scottpeterman@gmail.com
License: GPLv3
Classifier: Programming Language :: Python :: 3.9
Classifier: License :: OSI Approved :: GNU General Public License v3 (GPLv3)
Classifier: Operating System :: OS Independent
Requires-Python: >=3.9
Requires-Dist: asttokens ==2.2.1
Requires-Dist: bcrypt ==4.0.1
Requires-Dist: cffi ==1.15.1
Requires-Dist: cryptography ==41.0.1
Requires-Dist: paramiko ==3.2.0
Requires-Dist: pycparser ==2.21
Requires-Dist: pynetbox ==7.2.0
Requires-Dist: PyYAML ==6.0.1
Requires-Dist: PyNaCl ==1.5.0
Requires-Dist: pyte ==0.8.1
Requires-Dist: PyQt6 ==6.5.1
Requires-Dist: PyQt6-Qt6 ==6.5.1
Requires-Dist: PyQt6-sip ==13.5.1
Requires-Dist: PyQt6-WebEngine ==6.5.0
Requires-Dist: PyQt6-WebEngine-Qt6 ==6.5.1
Requires-Dist: cached-property ==1.5.2
Requires-Dist: greenlet ==3.0.0
Requires-Dist: inflection ==0.5.1
Requires-Dist: mypy-extensions ==1.0.0
Requires-Dist: SQLAlchemy ==2.0.21
Requires-Dist: sqlalchemy-orm ==1.2.10
Requires-Dist: typing-inspect ==0.9.0
Requires-Dist: typing-extensions ==4.8.0
Requires-Dist: wcwidth ==0.2.6
